{
  "description": "Provides a base structure for database bundle.",
  "baseFolder": "dbBlueprint",
  "textReplacements": {
    "[SymBundleName]": "symBunName",
    "[BundleName]" : "bundleName"
  },
  "requiredArguments": [
    {
      "argumentName": "bundleName",
      "mandatory": true,
      "defaultValue": ""
    },
    {
      "argumentName": "symBunName",
      "mandatory": true,
      "defaultValue": ""
    },
    {
      "argumentName": "targetDir",
      "mandatory": true,
      "defaultValue": ""
    }
  ],
  "name": "Database Project",
  "number": 2 
}